webpack_static
